<?xml version="1.0" encoding="utf-8"?>
<fmg>
<compression>None</compression>
<version>DarkSouls3</version>
<bigendian>False</bigendian>
<entries>
<text id="1376000">ミディールの深層にあった古い剣の記憶
それをソウルにより形作り、攻撃する魔術

攻撃は光波を伴い
攻撃前の構えを継続することで
その威力、速度が増す

古い剣の名は、これもまた月光であるが
白竜シースのそれとは、少し姿が異なる
その記憶は、よりはじまりに近いようだ</text>
<text id="1376010">ミディールの深層にあった古い剣の記憶
それをソウルにより形作り、攻撃する魔術

攻撃は光波を伴い
攻撃前の構えを継続することで
その威力、速度が増す

Increases Poise Damage to 100.

古い剣の名は、これもまた月光であるが
白竜シースのそれとは、少し姿が異なる
その記憶は、よりはじまりに近いようだ</text>
<text id="2458000">砂の呪術師の末裔、ゾーイの呪術
炎を扇とし、大きく打ち払う

また連続使用することで
炎の扇は左右に打ち払われる

砂の呪術師の例に漏れず、ゾーイもまた美しい
けれど彼女は、その美しさを毒とせず
ただ卑小な者たちの、細やかな女王となった</text>
<text id="2458010">砂の呪術師の末裔、ゾーイの呪術
炎を扇とし、大きく打ち払う

また連続使用することで
炎の扇は左右に打ち払われる
Can be used with no focus cost.

砂の呪術師の例に漏れず、ゾーイもまた美しい
けれど彼女は、その美しさを毒とせず
ただ卑小な者たちの、細やかな女王となった</text>
<text id="2660000">デーモンの王子が最後に灯した炎
混沌としたその欠片を、投げつける呪術

混沌の欠片は着弾地点で激しくたぎり
一瞬の収縮の後、大きく爆発する

デーモンにとって、それは命の欠片だっ</text>
<text id="2660010">デーモンの王子が最後に灯した炎
混沌としたその欠片を、投げつける呪術

混沌の欠片は着弾地点で激しくたぎり
一瞬の収縮の後、大きく爆発する
Increases Poise Damage to 100.

デーモンにとって、それは命の欠片だった</text>
<text id="3509000">神々の時代、数少ない女騎士たちが
竜狩りに用いた奇跡

雷の弓を引き絞り、雷の矢を射る

槍に比べて射程距離に優れ
彼方から竜の瞳を射抜いたともいう
美々しい物語には、誇張が付き物だ</text>
<text id="3509010">神々の時代、数少ない女騎士たちが
竜狩りに用いた奇跡

Draw lightning bow to fire a lightning arrow with no focus cost.

槍に比べて射程距離に優れ
彼方から竜の瞳を射抜いたともいう
美々しい物語には、誇張が付き物だ</text>
<text id="3557000">その終末期に、ロスリックで見出された奇跡

Toss a light that heals 300 HP for those near the point of impact.
Scales with Spell Buff.

太陽の光の王女
その癒しと恵みを忘れた人々は
それでもなお、彼女の後姿を思い描き
稚拙だが、真剣な物語を紡いだのだ</text>
<text id="3557010">その終末期に、ロスリックで見出された奇跡

Toss a light that heals 300 HP for those near the point of impact.
Scales with Spell Buff. Range increased to 5 meters.

太陽の光の王女
その癒しと恵みを忘れた人々は
それでもなお、彼女の後姿を思い描き
稚拙だが、真剣な物語を紡いだのだ</text>
</entries>
</fmg>